dmimport.py
dmimport-1.0.0.dist-info/DESCRIPTION.rst
dmimport-1.0.0.dist-info/METADATA
dmimport-1.0.0.dist-info/RECORD
dmimport-1.0.0.dist-info/WHEEL
dmimport-1.0.0.dist-info/metadata.json
dmimport-1.0.0.dist-info/top_level.txt
