Metadata-Version: 2.0
Name: dmimport
Version: 1.0.0
Summary: dmimport
Home-page: https://upload.pypi.org/legacy/dmimport
Author: dataminingmaster
Author-email: no-email.no-email@mail.com
License: MIT
Platform: any
